dogpile_breaker/__init__.py
dogpile_breaker/api.py
dogpile_breaker/backends/__init__.py
dogpile_breaker/backends/circuit_breaker_fallback_backend.py
dogpile_breaker/backends/memory_backend.py
dogpile_breaker/backends/redis_backend.py
dogpile_breaker/backends/redis_client.py
dogpile_breaker/exceptions.py
dogpile_breaker/models.py
dogpile_breaker/monitoring.py
dogpile_breaker/py.typed
dogpile_breaker-0.60.0.dist-info/WHEEL
dogpile_breaker-0.60.0.dist-info/METADATA
dogpile_breaker-0.60.0.dist-info/RECORD
