Metadata-Version: 2.3
Name: dogpile-breaker
Version: 0.60.0
Summary: Cache for Asyncio Applications with Anti-Dogpile Effect
Author: Dmitry P.
Author-email: Dmitry P. <wwarne@gmail.com>
Requires-Dist: async-timeout>=5.0.1 ; python_full_version < '3.11.3'
Requires-Dist: redis>=5.3
Requires-Dist: typing-extensions>=4.12.2
Requires-Dist: prometheus-client>=0.21.1 ; extra == 'metrics'
Requires-Python: >=3.10
Project-URL: Source, https://github.com/wwarne/dogpile_breaker/
Provides-Extra: metrics
